connectdb/cassandra_db.py
connectdb/mongodb.py
connectdb/mysql_db.py
connectdb-1.0.0.dist-info/LICENSE
connectdb-1.0.0.dist-info/METADATA
connectdb-1.0.0.dist-info/WHEEL
connectdb-1.0.0.dist-info/top_level.txt
connectdb-1.0.0.dist-info/RECORD
