Metadata-Version: 2.1
Name: connectdb
Version: 1.0.0
Summary: Connect python with Mysql, MongoDB, Cassandra database
Home-page: https://github.com/arjun-panwar/PyPi-connectdb
Author: Arjun Panwar
Author-email: arjunpanwar01@yahoo.com
License: MIT
Platform: UNKNOWN
Classifier: License :: OSI Approved :: MIT License
Classifier: Programming Language :: Python :: 3.6
Classifier: Programming Language :: Python :: 3.7
Classifier: Programming Language :: Python :: 3.8
Classifier: Programming Language :: Python :: 3.9
License-File: LICENSE
